collective.embeddedpage-4.0.0-py3.10-nspkg.pth
collective/embeddedpage/__init__.py
collective/embeddedpage/configure.zcml
collective/embeddedpage/interfaces.py
collective/embeddedpage/serializers.py
collective/embeddedpage/setuphandlers.py
collective/embeddedpage/testing.py
collective/embeddedpage/upgrades.py
collective/embeddedpage/upgrades.zcml
collective/embeddedpage/browser/__init__.py
collective/embeddedpage/browser/configure.zcml
collective/embeddedpage/browser/embeddedpage.pt
collective/embeddedpage/browser/embeddedpage.py
collective/embeddedpage/browser/overrides/.gitkeep
collective/embeddedpage/browser/static/.gitkeep
collective/embeddedpage/locales/collective.embeddedpage.pot
collective/embeddedpage/locales/update.sh
collective/embeddedpage/locales/ca/LC_MESSAGES/collective.embeddedpage.po
collective/embeddedpage/locales/de/LC_MESSAGES/collective.embeddedpage.po
collective/embeddedpage/locales/en/LC_MESSAGES/collective.embeddedpage.po
collective/embeddedpage/locales/es/LC_MESSAGES/collective.embeddedpage.po
collective/embeddedpage/profiles/default/browserlayer.xml
collective/embeddedpage/profiles/default/metadata.xml
collective/embeddedpage/profiles/default/registry.xml
collective/embeddedpage/profiles/default/types.xml
collective/embeddedpage/profiles/default/types/EmbeddedPage.xml
collective/embeddedpage/profiles/uninstall/browserlayer.xml
collective/embeddedpage/tests/__init__.py
collective/embeddedpage/tests/test_browser_embeddedpage.py
collective/embeddedpage/tests/test_embeddedpage.py
collective/embeddedpage/tests/test_robot.py
collective/embeddedpage/tests/test_serializers.py
collective/embeddedpage/tests/test_setup.py
collective/embeddedpage/tests/robot/test_embeddedpage.robot
collective.embeddedpage-4.0.0.dist-info/METADATA
collective.embeddedpage-4.0.0.dist-info/WHEEL
collective.embeddedpage-4.0.0.dist-info/entry_points.txt
collective.embeddedpage-4.0.0.dist-info/namespace_packages.txt
collective.embeddedpage-4.0.0.dist-info/top_level.txt
collective.embeddedpage-4.0.0.dist-info/RECORD
