Metadata-Version: 2.1
Name: collective.embeddedpage
Version: 4.0.0
Summary: Add-on to embed remote HTML pages into the Plone CMS
Home-page: https://pypi.python.org/pypi/collective.embeddedpage
Author: kitconcept GmbH
Author-email: info@kitconcept.com
License: GPL version 2
Keywords: Python Plone
Classifier: Development Status :: 5 - Production/Stable
Classifier: Environment :: Web Environment
Classifier: Framework :: Plone
Classifier: Framework :: Plone :: 5.2
Classifier: Framework :: Plone :: 6.0
Classifier: Programming Language :: Python
Classifier: Programming Language :: Python :: 3 :: Only
Classifier: Programming Language :: Python :: 3.7
Classifier: Programming Language :: Python :: 3.8
Classifier: Programming Language :: Python :: 3.9
Classifier: Programming Language :: Python :: 3.10
Classifier: Programming Language :: Python :: 3.11
Classifier: Operating System :: OS Independent
Classifier: License :: OSI Approved :: GNU General Public License v2 (GPLv2)
Requires-Python: >=3.7
Requires-Dist: chardet
Requires-Dist: lxml
Requires-Dist: plone.api
Requires-Dist: plone.app.contenttypes
Requires-Dist: plone.app.dexterity
Requires-Dist: plone.app.lockingbehavior
Requires-Dist: plone.app.relationfield
Requires-Dist: plone.app.versioningbehavior
Requires-Dist: plone.restapi
Requires-Dist: Products.GenericSetup >=1.8.2
Requires-Dist: requests
Requires-Dist: setuptools
Requires-Dist: z3c.jbot
Provides-Extra: test
Requires-Dist: cssselect ; extra == 'test'
Requires-Dist: httmock ; extra == 'test'
Requires-Dist: robotframework ; extra == 'test'
Requires-Dist: plone.app.testing ; extra == 'test'
Requires-Dist: plone.testing ; extra == 'test'
Requires-Dist: plone.app.contenttypes ; extra == 'test'
Requires-Dist: plone.app.robotframework[debug] ; extra == 'test'
Requires-Dist: zest.releaser[recommended] ; extra == 'test'
Requires-Dist: towncrier ; extra == 'test'
Requires-Dist: zestreleaser.towncrier ; extra == 'test'
Requires-Dist: wheel ; extra == 'test'
Requires-Dist: black ; extra == 'test'
Requires-Dist: isort ; extra == 'test'
Requires-Dist: flake8 ; extra == 'test'
